py2max/__init__.py
py2max/__main__.py
py2max/cli.py
py2max/core/__init__.py
py2max/core/abstract.py
py2max/core/box.py
py2max/core/common.py
py2max/core/patcher.py
py2max/core/patchline.py
py2max/exceptions.py
py2max/export/__init__.py
py2max/export/converters.py
py2max/export/svg.py
py2max/layout/__init__.py
py2max/layout/base.py
py2max/layout/flow.py
py2max/layout/grid.py
py2max/layout/matrix.py
py2max/log.py
py2max/maxref/__init__.py
py2max/maxref/category.py
py2max/maxref/db.py
py2max/maxref/legacy.py
py2max/maxref/parser.py
py2max/py.typed
py2max/server/__init__.py
py2max/server/client.py
py2max/server/inline.py
py2max/server/repl.py
py2max/server/rpc.py
py2max/server/websocket.py
py2max/static/cola.min.js
py2max/static/d3.v7.min.js
py2max/static/dagre-bundle.js
py2max/static/elk.bundled.js
py2max/static/index.html
py2max/static/interactive.html
py2max/static/interactive.js
py2max/static/live-preview.js
py2max/static/svg.min.js
py2max/static/svg.min.js.map
py2max/transformers.py
py2max/utils.py
py2max-0.2.1.dist-info/licenses/LICENSE
py2max-0.2.1.dist-info/WHEEL
py2max-0.2.1.dist-info/entry_points.txt
py2max-0.2.1.dist-info/METADATA
py2max-0.2.1.dist-info/RECORD
