Metadata-Version: 2.4
Name: py2max
Version: 0.2.1
Summary: A library for offline generation of Max/MSP patcher (.maxpat) files.
Keywords: Max,maxpat,offline
Author: Shakeeb Alireza
Author-email: Shakeeb Alireza <shakfu@users.noreply.github.com>
License-Expression: MIT
License-File: LICENSE
Classifier: Development Status :: 3 - Alpha
Classifier: Intended Audience :: Developers
Classifier: Intended Audience :: End Users/Desktop
Classifier: Topic :: Multimedia :: Sound/Audio
Classifier: Topic :: Software Development :: Libraries :: Python Modules
Classifier: License :: OSI Approved :: MIT License
Classifier: Programming Language :: Python :: 3
Classifier: Programming Language :: Python :: 3.9
Classifier: Programming Language :: Python :: 3.10
Classifier: Programming Language :: Python :: 3.11
Classifier: Programming Language :: Python :: 3.12
Classifier: Programming Language :: Python :: 3.13
Classifier: Programming Language :: Python :: 3.14
Classifier: Operating System :: OS Independent
Classifier: Typing :: Typed
Requires-Dist: websockets>=12.0 ; extra == 'server'
Requires-Dist: ptpython>=3.0.0 ; extra == 'server'
Requires-Python: >=3.9
Project-URL: Changelog, https://github.com/shakfu/py2max/blob/main/CHANGELOG.md
Project-URL: Documentation, https://github.com/shakfu/py2max#readme
Project-URL: Homepage, https://github.com/shakfu/py2max
Project-URL: Issues, https://github.com/shakfu/py2max/issues
Project-URL: Repository, https://github.com/shakfu/py2max.git
Provides-Extra: server
